aibasics/__cli__.py
aibasics/__init__.py
aibasics/_version.py
aibasics/conf/__init__.py
aibasics/conf/about/aibasics.yaml
aibasics/py.typed
aibasics-0.10.1.dist-info/LICENSE
aibasics-0.10.1.dist-info/METADATA
aibasics-0.10.1.dist-info/WHEEL
aibasics-0.10.1.dist-info/entry_points.txt
aibasics-0.10.1.dist-info/RECORD
