Metadata-Version: 2.1
Name: aibasics
Version: 0.10.1
Summary: AI Uncovered: A Comprehensive Guide to AI Basics and Applications
Home-page: https://aibasics.halla.ai
License: CC-BY-4.0
Author: Young Joon Lee
Author-email: yj.lee@chu.ac.kr
Requires-Python: >=3.9,<3.12
Classifier: License :: Other/Proprietary License
Classifier: Programming Language :: Python :: 3
Classifier: Programming Language :: Python :: 3.9
Classifier: Programming Language :: Python :: 3.10
Classifier: Programming Language :: Python :: 3.11
Requires-Dist: click (<=8.1.7)
Requires-Dist: hyfi (>=1.36.3,<2.0.0)
Requires-Dist: scikit-learn (<=1.4.1.post1)
Requires-Dist: seaborn (<=0.13.2)
Project-URL: Repository, https://github.com/chu-aie/aibasics
